<Properties StartupConfiguration="{0FA1E33C-24D1-4F6D-8142-9FEE538DC8B6}|Default">
  <MonoDevelop.Ide.Workbench ActiveDocument="Casino/FraudException.cs">
    <Files>
      <File FileName="Casino/Player.cs" />
      <File FileName="Casino/Dealer.cs" />
      <File FileName="Casino/TwentyOneGame.cs" Line="43" Column="48" />
      <File FileName="Casino/FraudException.cs" Line="9" Column="32" />
    </Files>
    <Pads>
      <Pad Id="ProjectPad">
        <State name="__root__">
          <Node name="TwentyOne" expanded="True">
            <Node name="Casino" expanded="True">
              <Node name="FraudException.cs" selected="True" />
            </Node>
            <Node name="TwentyOne" expanded="True" />
          </Node>
        </State>
      </Pad>
    </Pads>
  </MonoDevelop.Ide.Workbench>
  <MonoDevelop.Ide.DebuggingService.PinnedWatches />
  <MonoDevelop.Ide.Workspace ActiveConfiguration="Debug" />
  <MonoDevelop.Ide.ItemProperties.TwentyOne PreferredExecutionTarget="MonoDevelop.Default" />
  <MonoDevelop.Ide.DebuggingService.Breakpoints>
    <BreakpointStore />
  </MonoDevelop.Ide.DebuggingService.Breakpoints>
  <MultiItemStartupConfigurations />
</Properties>